{
  "project_info": {
    "project_number": "689545731886",
    "firebase_url": "https://mawareeth-adnan.firebaseio.com",
    "project_id": "mawareeth-adnan",
    "storage_bucket": "mawareeth-adnan.appspot.com"
  },
  "client": [
    {
      "client_info": {
        "mobilesdk_app_id": "1:689545731886:android:c688ad30adfbbe4939e4bf",
        "android_client_info": {
          "package_name": "com.company.mawarees"
        }
      },
      "oauth_client": [
        {
          "client_id": "689545731886-2fmoiam35banrbtkifl62q00nf1heu9v.apps.googleusercontent.com",
          "client_type": 1,
          "android_info": {
            "package_name": "com.company.mawarees",
            "certificate_hash": "2e535fb298e212ec319306dccd4a238938756a4a"
          }
        },
        {
          "client_id": "689545731886-a3dgke9qjhu0ni552g2587cec72aen9b.apps.googleusercontent.com",
          "client_type": 3
        }
      ],
      "api_key": [
        {
          "current_key": "AIzaSyA-BMYQmht607Yij0Bk9Bj-poefIFAgvkQ"
        }
      ],
      "services": {
        "appinvite_service": {
          "other_platform_oauth_client": [
            {
              "client_id": "689545731886-a3dgke9qjhu0ni552g2587cec72aen9b.apps.googleusercontent.com",
              "client_type": 3
            }
          ]
        }
      }
    }
  ],
  "configuration_version": "1"
}